cb58ref/__init__.py
cb58ref/__main__.py
cb58ref/base58.py
cb58ref/cli.py
cb58ref-0.2.0.dist-info/AUTHORS.rst
cb58ref-0.2.0.dist-info/LICENSE
cb58ref-0.2.0.dist-info/METADATA
cb58ref-0.2.0.dist-info/WHEEL
cb58ref-0.2.0.dist-info/top_level.txt
cb58ref-0.2.0.dist-info/zip-safe
cb58ref-0.2.0.dist-info/RECORD
