Metadata-Version: 2.1
Name: cb58ref
Version: 0.2.0
Summary: Reference implementation of CB58 encoding used by AVA
Home-page: https://github.com/moreati/cb58ref
Author: Alex Willmer
Author-email: alex@moreati.org.uk
License: MIT license
Keywords: cb58 base58 ava
Platform: UNKNOWN
Classifier: Development Status :: 2 - Pre-Alpha
Classifier: Intended Audience :: Developers
Classifier: License :: OSI Approved :: MIT License
Classifier: Natural Language :: English
Classifier: Programming Language :: Python :: 3 :: Only
Classifier: Programming Language :: Python :: 3.5
Classifier: Programming Language :: Python :: 3.6
Classifier: Programming Language :: Python :: 3.7
Classifier: Programming Language :: Python :: 3.8
Requires-Python: >=3.5
